{"name":"Lemon Pudding Dessert","ingredients":[{"quantity":"1 c. cold","name":"butter or margarine","type":""},{"quantity":"2 c.","name":"all purpose flour","type":""},{"quantity":"1 8 oz pkg","name":"cream cheese","type":""},{"quantity":"1 c.","name":"powdered sugar","type":""},{"quantity":"1 carton","name":"Cool Whip-thawed/divided","type":""},{"quantity":"3 c.","name":"cold milk","type":""},{"quantity":"2 pkg (3.4 ounces)","name":"instant lemon pudding mix","type":""}],"steps":["In a bowl, cut butter into the flour until crumbly. Press into an ungreased 13 x 9 baking pan. Bake at 350 for 18-22 minutes or until set. Cool on a wire rack. ","In a mixing bowl, beat cream cheese and sugar until smooth. Fold in 1 c. whipped topping. Spread over crust. In a mixing bowl, beat milk and pudding mix on low speed for 2 minutes. Carefully spread over the cream cheese layer. Top with remaining whipped topping. Refrigerate for at least 1 hour."],"timers":["",""]}